CHANGES.rst
CONTRIBUTORS.rst
MANIFEST.in
README.rst
VERSION
setup.cfg
setup.py
docs/LICENSE.GPL
docs/LICENSE.rst
docs/index.rst
src/visaplan/__init__.py
src/visaplan.plone.transform.egg-info/PKG-INFO
src/visaplan.plone.transform.egg-info/SOURCES.txt
src/visaplan.plone.transform.egg-info/dependency_links.txt
src/visaplan.plone.transform.egg-info/entry_points.txt
src/visaplan.plone.transform.egg-info/namespace_packages.txt
src/visaplan.plone.transform.egg-info/not-zip-safe
src/visaplan.plone.transform.egg-info/requires.txt
src/visaplan.plone.transform.egg-info/top_level.txt
src/visaplan/plone/__init__.py
src/visaplan/plone/transform/__init__.py
src/visaplan/plone/transform/browser.py
src/visaplan/plone/transform/config.py
src/visaplan/plone/transform/configure.zcml
src/visaplan/plone/transform/dispatcher.py
src/visaplan/plone/transform/kitchen.py
src/visaplan/plone/transform/oldfuncs.py
src/visaplan/plone/transform/profile-table.sql
src/visaplan/plone/transform/sniff.py
src/visaplan/plone/transform/test_transform.py
src/visaplan/plone/transform/tocspecs.py
src/visaplan/plone/transform/utils.py
src/visaplan/plone/transform/templates/__init__.py
src/visaplan/plone/transform/templates/code-audit.pt
src/visaplan/plone/transform/templates/configure.zcml
src/visaplan/plone/transform/templates/kss-file-view.pt
src/visaplan/plone/transform/templates/kss-image-view.pt
src/visaplan/plone/transform/templates/kss-table-view.pt
src/visaplan/plone/transform/templates/placeholder-error.pt
src/visaplan/plone/transform/templates/placeholder-unauthorized.pt
src/visaplan/plone/transform/testdata/0001-in.html
src/visaplan/plone/transform/testdata/0001-out.html